windrose/__init__.py
windrose/_version.py
windrose/windrose.py
windrose-1.9.2.dist-info/LICENCE_BSD-3-Clause.txt
windrose-1.9.2.dist-info/LICENCE_CECILL-B.txt
windrose-1.9.2.dist-info/METADATA
windrose-1.9.2.dist-info/WHEEL
windrose-1.9.2.dist-info/top_level.txt
windrose-1.9.2.dist-info/RECORD
