Metadata-Version: 2.1
Name: windrose
Version: 1.9.2
Summary: Python Matplotlib, Numpy library to manage wind data, draw windrose (also known as a polar rose plot)
Author-email: Lionel Roubeyrie <s.celles@gmail.co>
Maintainer: Sebastien Celles
Maintainer-email: Filipe Fernandes <ocefpaf+windrose@gmail.com>
License: BSD-3-Clause OR BCeCILL-B
Project-URL: documentation, https://python-windrose.github.io/windrose
Project-URL: homepage, https://github.com/python-windrose/windrose
Project-URL: repository, https://github.com/python-windrose/windrose
Classifier: Programming Language :: Python :: 3 :: Only
Classifier: Programming Language :: Python :: 3.8
Classifier: Programming Language :: Python :: 3.9
Classifier: Programming Language :: Python :: 3.10
Classifier: Programming Language :: Python :: 3.11
Classifier: Programming Language :: Python :: 3.12
Requires-Python: >=3.8
License-File: LICENCE_BSD-3-Clause.txt
License-File: LICENCE_CECILL-B.txt
Requires-Dist: matplotlib>=3
Requires-Dist: numpy>=1.21
Provides-Extra: extras
Requires-Dist: pandas; extra == "extras"
Requires-Dist: scipy; extra == "extras"
